eaanalytics/__init__.py
eaanalytics/controlfile/__init__.py
eaanalytics/controlfile/controlfile.py
eaanalytics/utils/__init__.py
eaanalytics/utils/utils.py
eaanalytics-0.0.2.dist-info/LICENSE
eaanalytics-0.0.2.dist-info/METADATA
eaanalytics-0.0.2.dist-info/WHEEL
eaanalytics-0.0.2.dist-info/top_level.txt
eaanalytics-0.0.2.dist-info/RECORD
