Metadata-Version: 2.1
Name: eaanalytics
Version: 0.0.2
Summary: This package serves to guide and facilitate the development of scripts for application management.
Home-page: https://github.com/leansouza/eaanalytics
Author: Leanderson Souza
Author-email: leandersonsantana@ioasys.com.br
Classifier: Programming Language :: Python :: 3
Classifier: License :: OSI Approved :: MIT License
Classifier: Operating System :: OS Independent
Requires-Python: >=3.7
License-File: LICENSE
